aws_testlib/__init__.py
aws_testlib/apigw/__init__.py
aws_testlib/apigw/java/__init__.py
aws_testlib/apigw/java/aws-apigateway-velocity-repl.jar
aws_testlib/apigw/template.py
aws_testlib-0.1.11.dist-info/METADATA
aws_testlib-0.1.11.dist-info/WHEEL
aws_testlib-0.1.11.dist-info/RECORD
