Metadata-Version: 2.1
Name: aws-testlib
Version: 0.1.11
Summary: Provides support functions for testing AWS testing and mocking, namely AWS API Gateway Velocity engine
Author: Martin Macak
Author-email: martin.macak@gmail.com
Requires-Python: >=3.10,<3.14
Classifier: Programming Language :: Python :: 3
Classifier: Programming Language :: Python :: 3.10
Classifier: Programming Language :: Python :: 3.11
Classifier: Programming Language :: Python :: 3.12
Classifier: Programming Language :: Python :: 3.13
